pyco/__init__.py
pyco/basis.py
pyco/cirkel.py
pyco/data.py
pyco/document.py
pyco/doorsnede.py
pyco/figuur.py
pyco/functions.py
pyco/knoop.py
pyco/lijn.py
pyco/lijst.py
pyco/macro.py
pyco/materiaal.py
pyco/rechthoek.py
pyco/tabel.py
pyco/vector.py
pyco/venster.py
pyco/vorm.py
pyco/waarde.py
pyco/bieb_modules/__init__.py
pyco/bieb_modules/beton_data.py
pyco/bieb_modules/ligger_op_twee_steunpunten.py
pyconl-0.4.4.dist-info/LICENSE.txt
pyconl-0.4.4.dist-info/METADATA
pyconl-0.4.4.dist-info/WHEEL
pyconl-0.4.4.dist-info/top_level.txt
pyconl-0.4.4.dist-info/RECORD
