Metadata-Version: 2.1
Name: pyconl
Version: 0.4.4
Summary: Civiel Technisch ontwerpen in Python.
Home-page: https://github.com/ornor/pyco
Author: Jara van Veldhoven
Author-email: jarav@nveldhoven.nl
Classifier: Programming Language :: Python :: 3
Classifier: License :: OSI Approved :: GNU General Public License v3 (GPLv3)
Classifier: Operating System :: OS Independent
Classifier: Natural Language :: Dutch
License-File: LICENSE.txt
